recoding/__init__.py
recoding/__main__.py
recoding/code.py
recoding-0.0.2.dist-info/licenses/LICENSE
recoding-0.0.2.dist-info/METADATA
recoding-0.0.2.dist-info/WHEEL
recoding-0.0.2.dist-info/top_level.txt
recoding-0.0.2.dist-info/RECORD
